google_api_client_wrapper-2.0.0.dist-info/licenses/LICENSE
google_client/__init__.py
google_client/api_service.py
google_client/auth.py
google_client/services/__init__.py
google_client/services/calendar/__init__.py
google_client/services/calendar/api_service.py
google_client/services/calendar/async_api_service.py
google_client/services/calendar/async_query_builder.py
google_client/services/calendar/constants.py
google_client/services/calendar/query_builder.py
google_client/services/calendar/types.py
google_client/services/calendar/utils.py
google_client/services/drive/__init__.py
google_client/services/drive/api_service.py
google_client/services/drive/async_api_service.py
google_client/services/drive/async_query_builder.py
google_client/services/drive/constants.py
google_client/services/drive/exceptions.py
google_client/services/drive/query_builder.py
google_client/services/drive/types.py
google_client/services/drive/utils.py
google_client/services/gmail/__init__.py
google_client/services/gmail/api_service.py
google_client/services/gmail/async_api_service.py
google_client/services/gmail/async_query_builder.py
google_client/services/gmail/constants.py
google_client/services/gmail/query_builder.py
google_client/services/gmail/types.py
google_client/services/gmail/utils.py
google_client/services/tasks/__init__.py
google_client/services/tasks/api_service.py
google_client/services/tasks/async_api_service.py
google_client/services/tasks/async_query_builder.py
google_client/services/tasks/constants.py
google_client/services/tasks/query_builder.py
google_client/services/tasks/types.py
google_client/services/tasks/utils.py
google_client/utils/__init__.py
google_client/utils/datetime.py
google_client/utils/validation.py
google_api_client_wrapper-2.0.0.dist-info/METADATA
google_api_client_wrapper-2.0.0.dist-info/WHEEL
google_api_client_wrapper-2.0.0.dist-info/top_level.txt
google_api_client_wrapper-2.0.0.dist-info/RECORD
