Metadata-Version: 2.4
Name: google-api-client-wrapper
Version: 2.0.0
Summary: A comprehensive Python wrapper for Google APIs with async support, providing clean and intuitive access to Gmail, Google Drive, Google Calendar, and Google Tasks services.
Author-email: Dagmawi Molla <dagmawishewadeg@gmail.com>
License: MIT License
Project-URL: Homepage, https://github.com/dsmolla/google-api-client-wrapper
Project-URL: Documentation, https://github.com/dsmolla/google-api-wrapper/blob/main/README.md
Project-URL: Repository, https://github.com/dsmolla/google-api-client-wrapper
Keywords: google-api,gmail,google-drive,google-calendar,google-tasks,api-wrapper,python-wrapper
Classifier: Programming Language :: Python :: 3
Classifier: License :: OSI Approved :: MIT License
Classifier: Operating System :: OS Independent
Classifier: Intended Audience :: Developers
Classifier: Topic :: Software Development :: Libraries :: Python Modules
Requires-Python: >=3.9
License-File: LICENSE
Requires-Dist: google-api-python-client>=2.163.0
Requires-Dist: google-auth>=2.28.1
Requires-Dist: google-auth-httplib2
Requires-Dist: google-auth-oauthlib>=1.2.1
Requires-Dist: tzlocal>=5.3.1
Requires-Dist: html2text>=2025.4.15
Requires-Dist: pydantic>=2.11.7
Requires-Dist: aiohttp>=3.9.0
Requires-Dist: aiofiles>=23.0.0
Requires-Dist: aiogoogle>=5.15.0
Dynamic: license-file
